dataclass_bakery_patched/__init__.py
dataclass_bakery_patched/baker.py
dataclass_bakery_patched/generators/__init__.py
dataclass_bakery_patched/generators/defaults.py
dataclass_bakery_patched/generators/generators_exceptions.py
dataclass_bakery_patched/generators/random_bool_generator.py
dataclass_bakery_patched/generators/random_complex_generator.py
dataclass_bakery_patched/generators/random_data_class_generator.py
dataclass_bakery_patched/generators/random_decimal_generator.py
dataclass_bakery_patched/generators/random_dict_generator.py
dataclass_bakery_patched/generators/random_enum_generator.py
dataclass_bakery_patched/generators/random_float_generator.py
dataclass_bakery_patched/generators/random_generator.py
dataclass_bakery_patched/generators/random_int_generator.py
dataclass_bakery_patched/generators/random_list_generator.py
dataclass_bakery_patched/generators/random_option_generator.py
dataclass_bakery_patched/generators/random_path_generator.py
dataclass_bakery_patched/generators/random_range_generator.py
dataclass_bakery_patched/generators/random_set_generator.py
dataclass_bakery_patched/generators/random_str_generator.py
dataclass_bakery_patched/generators/random_tuple_generator.py
dataclass_bakery_patched/generators/random_uuid_generator.py
dataclass_bakery_patched-0.6.0.dist-info/LICENSE
dataclass_bakery_patched-0.6.0.dist-info/METADATA
dataclass_bakery_patched-0.6.0.dist-info/WHEEL
dataclass_bakery_patched-0.6.0.dist-info/RECORD
