Metadata-Version: 2.1
Name: dataclass-bakery-patched
Version: 0.6.0
Summary: A fork from dataclass-bakery, with a tweak to consider inherited attributes when creating dataclasses.
Author: Adam Ruman
Author-email: 469068@muni.cz
Requires-Python: >=3.11,<4.0
Classifier: Programming Language :: Python :: 3
Classifier: Programming Language :: Python :: 3.11
